payment_parser/__init__.py
payment_parser/__main__.py
payment_parser/helpers.py
payment_parser-0.2.3.dist-info/LICENSE.md
payment_parser-0.2.3.dist-info/METADATA
payment_parser-0.2.3.dist-info/WHEEL
payment_parser-0.2.3.dist-info/top_level.txt
payment_parser-0.2.3.dist-info/RECORD
