Metadata-Version: 2.1
Name: payment-parser
Version: 0.2.3
Summary: Python Script for Parsing Payments File.
Home-page: https://github.com/org-not-included/payment_parser/
Author: ['shivanjaywagh', 'mtsadler']
Keywords: T140,payment,parser,fixed,width,format
Classifier: Intended Audience :: Developers
Classifier: Programming Language :: Python :: 3
Classifier: Operating System :: Unix
Classifier: Operating System :: MacOS :: MacOS X
Classifier: Operating System :: Microsoft :: Windows
License-File: LICENSE.md
Requires-Dist: pandas
